pdor/__init__.py
pdor/configs.ini
pdor/pdor_exception.py
pdor/pdor_llm.py
pdor/pdor_out.py
pdor/pdor_pattern.py
pdor/pdor_unit.py
pdor/pdor_utils.py
pdor-0.2.0.dist-info/METADATA
pdor-0.2.0.dist-info/WHEEL
pdor-0.2.0.dist-info/top_level.txt
pdor-0.2.0.dist-info/RECORD
