Metadata-Version: 2.1
Name: pdor
Version: 0.2.0
Summary: PDF OCR识别工具，用于自动文档提取和分析
Home-page: https://github.com/Water-Run/pdor
Author: WaterRun
Author-email: 2263633954@qq.com
Classifier: Programming Language :: Python :: 3
Classifier: Programming Language :: Python :: 3.10
Classifier: License :: OSI Approved :: MIT License
Classifier: Operating System :: OS Independent
Classifier: Intended Audience :: Developers
Classifier: Topic :: Software Development :: Libraries :: Python Modules
Classifier: Topic :: Text Processing :: General
Classifier: Topic :: Scientific/Engineering :: Image Processing
Requires-Python: >=3.10
Requires-Dist: PyPDF2
Requires-Dist: pdf2image
Requires-Dist: opencv-python
Requires-Dist: numpy
Requires-Dist: simpsave
Requires-Dist: pandas
Requires-Dist: openpyxl
Requires-Dist: pyyaml
Requires-Dist: toml
Requires-Dist: requests
